msys2dl/__init__.py
msys2dl/application.py
msys2dl/commands/__init__.py
msys2dl/commands/command.py
msys2dl/commands/command_extract.py
msys2dl/commands/command_make_deb.py
msys2dl/commands/output_dir_mixin.py
msys2dl/commands/package_set_mixin.py
msys2dl/download/__init__.py
msys2dl/download/callback_registry.py
msys2dl/download/download_callback.py
msys2dl/download/download_request.py
msys2dl/download/parallel_downloader.py
msys2dl/download/simple_downloader.py
msys2dl/gpg_keyring.py
msys2dl/main.py
msys2dl/package.py
msys2dl/package_database.py
msys2dl/package_store.py
msys2dl/progress.py
msys2dl/utilities.py
msys2dl-2.1.1.dist-info/LICENSE
msys2dl-2.1.1.dist-info/METADATA
msys2dl-2.1.1.dist-info/WHEEL
msys2dl-2.1.1.dist-info/entry_points.txt
msys2dl-2.1.1.dist-info/RECORD
